<?xml version="1.0" encoding="UTF-8"?>
<con:operation id="cc9fc75d-ab85-4387-ab3f-ff5325bc4681" isOneWay="false" action="" name="LanguageISOCode" bindingOperationName="LanguageISOCode" type="Request-Response" inputName="" receivesAttachments="false" sendsAttachments="false" anonymous="optional" xmlns:xsi="http://www.w3.org/2001/XMLSchema-instance" xmlns:con="http://eviware.com/soapui/config"><con:settings><con:setting id="cc9fc75d-ab85-4387-ab3f-ff5325bc4681fileName">LanguageISOCode</con:setting></con:settings><con:call id="caafa076-6074-4929-8798-165be5caa77e" name="Request 1"><con:settings/><con:encoding>UTF-8</con:encoding><con:endpoint>http://webservices.oorsprong.org/websamples.countryinfo/CountryInfoService.wso</con:endpoint><con:request><![CDATA[<soapenv:Envelope xmlns:soapenv="http://schemas.xmlsoap.org/soap/envelope/" xmlns:web="http://www.oorsprong.org/websamples.countryinfo">
   <soapenv:Header/>
   <soapenv:Body>
      <web:LanguageISOCode>
         <web:sLanguageName>?</web:sLanguageName>
      </web:LanguageISOCode>
   </soapenv:Body>
</soapenv:Envelope>]]></con:request><con:credentials><con:selectedAuthProfile>No Authorization</con:selectedAuthProfile><con:authType>No Authorization</con:authType></con:credentials><con:wsaConfig mustUnderstand="NONE" version="200508" action="http://www.oorsprong.org/websamples.countryinfo/CountryInfoServiceSoapType/LanguageISOCodeRequest"/></con:call></con:operation>