<?xml version="1.0" encoding="UTF-8"?>
<con:operation id="e0592ca2-2a4c-4a36-894e-2a9496114787" isOneWay="false" action="" name="ListOfLanguagesByName" bindingOperationName="ListOfLanguagesByName" type="Request-Response" inputName="" receivesAttachments="false" sendsAttachments="false" anonymous="optional" xmlns:xsi="http://www.w3.org/2001/XMLSchema-instance" xmlns:con="http://eviware.com/soapui/config"><con:settings><con:setting id="e0592ca2-2a4c-4a36-894e-2a9496114787fileName">ListOfLanguagesByName</con:setting></con:settings><con:call id="6abd0382-b00e-4ac4-b63e-e2aaf0fad43b" name="Request 1"><con:settings/><con:encoding>UTF-8</con:encoding><con:endpoint>http://webservices.oorsprong.org/websamples.countryinfo/CountryInfoService.wso</con:endpoint><con:request><![CDATA[<soap:Envelope xmlns:soap="http://www.w3.org/2003/05/soap-envelope" xmlns:web="http://www.oorsprong.org/websamples.countryinfo">
   <soap:Header/>
   <soap:Body>
      <web:ListOfLanguagesByName/>
   </soap:Body>
</soap:Envelope>]]></con:request><con:credentials><con:selectedAuthProfile>No Authorization</con:selectedAuthProfile><con:authType>No Authorization</con:authType></con:credentials><con:wsaConfig mustUnderstand="NONE" version="200508" action="http://www.oorsprong.org/websamples.countryinfo/CountryInfoServiceSoapType/ListOfLanguagesByNameRequest"/></con:call></con:operation>